<?xml version="1.0" encoding="UTF-8"?><?xml-stylesheet type='text/xsl' href='_UpgradeReport_Files/UpgradeReport.xslt'?><UpgradeLog>
<Properties><Property Name="Solution" Value="Cadastro">
</Property><Property Name="Solution File" Value="C:\Users\Alex\Downloads\Pendrive\Projects\Cadastro\Cadastro.sln">
</Property><Property Name="User Options File" Value="C:\Users\Alex\Downloads\Pendrive\Projects\Cadastro\Cadastro.suo">
</Property><Property Name="Date" Value="sexta-feira, 24 de junho de 2011">
</Property><Property Name="Time" Value="17:26">
</Property></Properties><Event ErrorLevel="0" Project="" Source="Cadastro.sln" Description="File successfully backed up as C:\Users\Alex\Downloads\Pendrive\Projects\Cadastro\Backup\Cadastro.sln">
</Event><Event ErrorLevel="0" Project="" Source="Cadastro.suo" Description="File successfully backed up as C:\Users\Alex\Downloads\Pendrive\Projects\Cadastro\Backup\Cadastro.suo">
</Event><Event ErrorLevel="0" Project="Cadastro" Source="Cadastro\Cadastro.csproj" Description="Project file successfully backed up as C:\Users\Alex\Downloads\Pendrive\Projects\Cadastro\Backup\Cadastro\Cadastro.csproj">
</Event><Event ErrorLevel="0" Project="Cadastro" Source="Cadastro\Endereco.cs" Description="File successfully backed up as C:\Users\Alex\Downloads\Pendrive\Projects\Cadastro\Backup\Cadastro\Endereco.cs">
</Event><Event ErrorLevel="0" Project="Cadastro" Source="Cadastro\Form1.cs" Description="File successfully backed up as C:\Users\Alex\Downloads\Pendrive\Projects\Cadastro\Backup\Cadastro\Form1.cs">
</Event><Event ErrorLevel="0" Project="Cadastro" Source="Cadastro\Form1.Designer.cs" Description="File successfully backed up as C:\Users\Alex\Downloads\Pendrive\Projects\Cadastro\Backup\Cadastro\Form1.Designer.cs">
</Event><Event ErrorLevel="0" Project="Cadastro" Source="Cadastro\Funcionario.cs" Description="File successfully backed up as C:\Users\Alex\Downloads\Pendrive\Projects\Cadastro\Backup\Cadastro\Funcionario.cs">
</Event><Event ErrorLevel="0" Project="Cadastro" Source="Cadastro\Program.cs" Description="File successfully backed up as C:\Users\Alex\Downloads\Pendrive\Projects\Cadastro\Backup\Cadastro\Program.cs">
</Event><Event ErrorLevel="0" Project="Cadastro" Source="Cadastro\Properties\AssemblyInfo.cs" Description="File successfully backed up as C:\Users\Alex\Downloads\Pendrive\Projects\Cadastro\Backup\Cadastro\Properties\AssemblyInfo.cs">
</Event><Event ErrorLevel="0" Project="Cadastro" Source="Cadastro\Properties\Resources.Designer.cs" Description="File successfully backed up as C:\Users\Alex\Downloads\Pendrive\Projects\Cadastro\Backup\Cadastro\Properties\Resources.Designer.cs">
</Event><Event ErrorLevel="0" Project="Cadastro" Source="Cadastro\Properties\Settings.Designer.cs" Description="File successfully backed up as C:\Users\Alex\Downloads\Pendrive\Projects\Cadastro\Backup\Cadastro\Properties\Settings.Designer.cs">
</Event><Event ErrorLevel="0" Project="Cadastro" Source="Cadastro\Properties\Settings.settings" Description="File successfully backed up as C:\Users\Alex\Downloads\Pendrive\Projects\Cadastro\Backup\Cadastro\Properties\Settings.settings">
</Event><Event ErrorLevel="0" Project="Cadastro" Source="Cadastro\Form1.resx" Description="File successfully backed up as C:\Users\Alex\Downloads\Pendrive\Projects\Cadastro\Backup\Cadastro\Form1.resx">
</Event><Event ErrorLevel="0" Project="Cadastro" Source="Cadastro\Properties\Resources.resx" Description="File successfully backed up as C:\Users\Alex\Downloads\Pendrive\Projects\Cadastro\Backup\Cadastro\Properties\Resources.resx">
</Event><Event ErrorLevel="0" Project="Cadastro" Source="Cadastro\Cadastro.csproj" Description="Project converted successfully">
</Event><Event ErrorLevel="3" Project="Cadastro" Source="Cadastro\Cadastro.csproj" Description="Converted">
</Event><Event ErrorLevel="0" Project="" Source="Cadastro.sln" Description="Solution converted successfully">
</Event><Event ErrorLevel="3" Project="" Source="Cadastro.sln" Description="Converted">
</Event><Event ErrorLevel="0" Project="Cadastro" Source="Cadastro\Cadastro.csproj" Description="Scan complete: Upgrade not required for project files.">
</Event></UpgradeLog>